{
    "description": "tray vertical 3x3x21",
    "id": "oobb_tray_vertical_03_03_21",
    "type": "tray_vertical",
    "width": 3,
    "height": 3,
    "thickness": 21,
    "width_mm": 44,
    "thickness_mm": 21,
    "height_mm": 44,
    "components": [
        {
            "type": "p",
            "shape": "rounded_rectangle",
            "size": [
                44,
                44,
                21
            ],
            "pos": [
                0,
                0,
                0
            ],
            "height": 3,
            "width": 3,
            "m": ""
        },
        {
            "type": "n",
            "shape": "sphere_rectangle",
            "size": [
                42,
                42,
                41
            ],
            "r": 4,
            "pos": [
                0,
                0,
                3
            ],
            "m": ""
        },
        {
            "type": "n",
            "shape": "cylinder",
            "r1": 2.4,
            "r2": 2.4,
            "h": 3,
            "pos": [
                -15.0,
                -15.0,
                0
            ],
            "inclusion": "laser",
            "height": 3,
            "width": 3,
            "m": "",
            "depth": 6
        },
        {
            "type": "n",
            "shape": "cylinder",
            "r1": 1.8,
            "r2": 3.6,
            "h": 1.9,
            "pos": [
                -15.0,
                -15.0,
                1.1
            ],
            "inclusion": "3dpr",
            "height": 3,
            "width": 3,
            "m": "",
            "depth": 6
        },
        {
            "type": "n",
            "shape": "cylinder",
            "r1": 3.6,
            "r2": 3.6,
            "h": 250,
            "pos": [
                -15.0,
                -15.0,
                3.0
            ],
            "inclusion": "3dpr",
            "height": 3,
            "width": 3,
            "m": "",
            "depth": 6
        },
        {
            "type": "n",
            "shape": "cylinder",
            "r1": 1.5,
            "r2": 2.9,
            "h": 1.7,
            "pos": [
                -15.0,
                -15.0,
                1.3
            ],
            "inclusion": "true",
            "height": 3,
            "width": 3,
            "m": "",
            "depth": 6
        },
        {
            "type": "n",
            "shape": "cylinder",
            "r": 1.5,
            "h": 6,
            "pos": [
                -15.0,
                -15.0,
                -3
            ],
            "inclusion": "laser",
            "height": 3,
            "width": 3,
            "m": "",
            "depth": 6
        },
        {
            "type": "n",
            "shape": "cylinder",
            "r": 1.8,
            "h": 6,
            "pos": [
                -15.0,
                -15.0,
                -3
            ],
            "inclusion": "3dpr",
            "height": 3,
            "width": 3,
            "m": "",
            "depth": 6
        },
        {
            "type": "n",
            "shape": "cylinder",
            "r": 1.5,
            "h": 6,
            "pos": [
                -15.0,
                -15.0,
                -3
            ],
            "inclusion": "true",
            "height": 3,
            "width": 3,
            "m": "",
            "depth": 6
        },
        {
            "type": "n",
            "shape": "cylinder",
            "r1": 2.4,
            "r2": 2.4,
            "h": 3,
            "pos": [
                15.0,
                -15.0,
                0
            ],
            "inclusion": "laser",
            "height": 3,
            "width": 3,
            "m": "",
            "depth": 6
        },
        {
            "type": "n",
            "shape": "cylinder",
            "r1": 1.8,
            "r2": 3.6,
            "h": 1.9,
            "pos": [
                15.0,
                -15.0,
                1.1
            ],
            "inclusion": "3dpr",
            "height": 3,
            "width": 3,
            "m": "",
            "depth": 6
        },
        {
            "type": "n",
            "shape": "cylinder",
            "r1": 3.6,
            "r2": 3.6,
            "h": 250,
            "pos": [
                15.0,
                -15.0,
                3.0
            ],
            "inclusion": "3dpr",
            "height": 3,
            "width": 3,
            "m": "",
            "depth": 6
        },
        {
            "type": "n",
            "shape": "cylinder",
            "r1": 1.5,
            "r2": 2.9,
            "h": 1.7,
            "pos": [
                15.0,
                -15.0,
                1.3
            ],
            "inclusion": "true",
            "height": 3,
            "width": 3,
            "m": "",
            "depth": 6
        },
        {
            "type": "n",
            "shape": "cylinder",
            "r": 1.5,
            "h": 6,
            "pos": [
                15.0,
                -15.0,
                -3
            ],
            "inclusion": "laser",
            "height": 3,
            "width": 3,
            "m": "",
            "depth": 6
        },
        {
            "type": "n",
            "shape": "cylinder",
            "r": 1.8,
            "h": 6,
            "pos": [
                15.0,
                -15.0,
                -3
            ],
            "inclusion": "3dpr",
            "height": 3,
            "width": 3,
            "m": "",
            "depth": 6
        },
        {
            "type": "n",
            "shape": "cylinder",
            "r": 1.5,
            "h": 6,
            "pos": [
                15.0,
                -15.0,
                -3
            ],
            "inclusion": "true",
            "height": 3,
            "width": 3,
            "m": "",
            "depth": 6
        },
        {
            "type": "n",
            "shape": "cylinder",
            "r1": 2.4,
            "r2": 2.4,
            "h": 3,
            "pos": [
                -15.0,
                15.0,
                0
            ],
            "inclusion": "laser",
            "height": 3,
            "width": 3,
            "m": "",
            "depth": 6
        },
        {
            "type": "n",
            "shape": "cylinder",
            "r1": 1.8,
            "r2": 3.6,
            "h": 1.9,
            "pos": [
                -15.0,
                15.0,
                1.1
            ],
            "inclusion": "3dpr",
            "height": 3,
            "width": 3,
            "m": "",
            "depth": 6
        },
        {
            "type": "n",
            "shape": "cylinder",
            "r1": 3.6,
            "r2": 3.6,
            "h": 250,
            "pos": [
                -15.0,
                15.0,
                3.0
            ],
            "inclusion": "3dpr",
            "height": 3,
            "width": 3,
            "m": "",
            "depth": 6
        },
        {
            "type": "n",
            "shape": "cylinder",
            "r1": 1.5,
            "r2": 2.9,
            "h": 1.7,
            "pos": [
                -15.0,
                15.0,
                1.3
            ],
            "inclusion": "true",
            "height": 3,
            "width": 3,
            "m": "",
            "depth": 6
        },
        {
            "type": "n",
            "shape": "cylinder",
            "r": 1.5,
            "h": 6,
            "pos": [
                -15.0,
                15.0,
                -3
            ],
            "inclusion": "laser",
            "height": 3,
            "width": 3,
            "m": "",
            "depth": 6
        },
        {
            "type": "n",
            "shape": "cylinder",
            "r": 1.8,
            "h": 6,
            "pos": [
                -15.0,
                15.0,
                -3
            ],
            "inclusion": "3dpr",
            "height": 3,
            "width": 3,
            "m": "",
            "depth": 6
        },
        {
            "type": "n",
            "shape": "cylinder",
            "r": 1.5,
            "h": 6,
            "pos": [
                -15.0,
                15.0,
                -3
            ],
            "inclusion": "true",
            "height": 3,
            "width": 3,
            "m": "",
            "depth": 6
        },
        {
            "type": "n",
            "shape": "cylinder",
            "r1": 2.4,
            "r2": 2.4,
            "h": 3,
            "pos": [
                15.0,
                15.0,
                0
            ],
            "inclusion": "laser",
            "height": 3,
            "width": 3,
            "m": "",
            "depth": 6
        },
        {
            "type": "n",
            "shape": "cylinder",
            "r1": 1.8,
            "r2": 3.6,
            "h": 1.9,
            "pos": [
                15.0,
                15.0,
                1.1
            ],
            "inclusion": "3dpr",
            "height": 3,
            "width": 3,
            "m": "",
            "depth": 6
        },
        {
            "type": "n",
            "shape": "cylinder",
            "r1": 3.6,
            "r2": 3.6,
            "h": 250,
            "pos": [
                15.0,
                15.0,
                3.0
            ],
            "inclusion": "3dpr",
            "height": 3,
            "width": 3,
            "m": "",
            "depth": 6
        },
        {
            "type": "n",
            "shape": "cylinder",
            "r1": 1.5,
            "r2": 2.9,
            "h": 1.7,
            "pos": [
                15.0,
                15.0,
                1.3
            ],
            "inclusion": "true",
            "height": 3,
            "width": 3,
            "m": "",
            "depth": 6
        },
        {
            "type": "n",
            "shape": "cylinder",
            "r": 1.5,
            "h": 6,
            "pos": [
                15.0,
                15.0,
                -3
            ],
            "inclusion": "laser",
            "height": 3,
            "width": 3,
            "m": "",
            "depth": 6
        },
        {
            "type": "n",
            "shape": "cylinder",
            "r": 1.8,
            "h": 6,
            "pos": [
                15.0,
                15.0,
                -3
            ],
            "inclusion": "3dpr",
            "height": 3,
            "width": 3,
            "m": "",
            "depth": 6
        },
        {
            "type": "n",
            "shape": "cylinder",
            "r": 1.5,
            "h": 6,
            "pos": [
                15.0,
                15.0,
                -3
            ],
            "inclusion": "true",
            "height": 3,
            "width": 3,
            "m": "",
            "depth": 6
        },
        {
            "type": "p",
            "shape": "rounded_rectangle",
            "size": [
                30,
                45,
                3
            ],
            "pos": [
                -21.0,
                0,
                15
            ],
            "rotY": 90,
            "m": ""
        },
        {
            "type": "n",
            "shape": "cylinder",
            "r": 3.0,
            "h": 300,
            "pos": [
                -37.5,
                -15.0,
                22.5
            ],
            "rotY": 90,
            "inclusion": "laser",
            "m": "#",
            "depth": 300
        },
        {
            "type": "n",
            "shape": "cylinder",
            "r": 3.25,
            "h": 300,
            "pos": [
                -37.5,
                -15.0,
                22.5
            ],
            "rotY": 90,
            "inclusion": "3dpr",
            "m": "#",
            "depth": 300
        },
        {
            "type": "n",
            "shape": "cylinder",
            "r": 3.0,
            "h": 300,
            "pos": [
                -37.5,
                -15.0,
                22.5
            ],
            "rotY": 90,
            "inclusion": "true",
            "m": "#",
            "depth": 300
        },
        {
            "type": "n",
            "shape": "cylinder",
            "r": 3.0,
            "h": 300,
            "pos": [
                -37.5,
                0.0,
                22.5
            ],
            "rotY": 90,
            "inclusion": "laser",
            "m": "#",
            "depth": 300
        },
        {
            "type": "n",
            "shape": "cylinder",
            "r": 3.25,
            "h": 300,
            "pos": [
                -37.5,
                0.0,
                22.5
            ],
            "rotY": 90,
            "inclusion": "3dpr",
            "m": "#",
            "depth": 300
        },
        {
            "type": "n",
            "shape": "cylinder",
            "r": 3.0,
            "h": 300,
            "pos": [
                -37.5,
                0.0,
                22.5
            ],
            "rotY": 90,
            "inclusion": "true",
            "m": "#",
            "depth": 300
        },
        {
            "type": "n",
            "shape": "cylinder",
            "r": 3.0,
            "h": 300,
            "pos": [
                -37.5,
                15.0,
                22.5
            ],
            "rotY": 90,
            "inclusion": "laser",
            "m": "#",
            "depth": 300
        },
        {
            "type": "n",
            "shape": "cylinder",
            "r": 3.25,
            "h": 300,
            "pos": [
                -37.5,
                15.0,
                22.5
            ],
            "rotY": 90,
            "inclusion": "3dpr",
            "m": "#",
            "depth": 300
        },
        {
            "type": "n",
            "shape": "cylinder",
            "r": 3.0,
            "h": 300,
            "pos": [
                -37.5,
                15.0,
                22.5
            ],
            "rotY": 90,
            "inclusion": "true",
            "m": "#",
            "depth": 300
        }
    ]
}