{
    "description": "bearing 6702",
    "id": "hardware_bearing_6702",
    "type": "bearing",
    "bearing_name": "6702",
    "components": [
        {
            "type": "positive",
            "shape": "cylinder",
            "r": 10.5,
            "h": 4,
            "inclusion": "laser",
            "depth": "bearing_6702_depth"
        },
        {
            "type": "positive",
            "shape": "cylinder",
            "r": 10.7,
            "h": 4,
            "inclusion": "3dpr",
            "depth": "bearing_6702_depth"
        },
        {
            "type": "positive",
            "shape": "cylinder",
            "r": 10.5,
            "h": 4,
            "inclusion": "true",
            "depth": "bearing_6702_depth"
        },
        {
            "type": "negative",
            "shape": "cylinder",
            "r": 7.5,
            "h": 4,
            "inclusion": "laser",
            "depth": "bearing_6702_depth"
        },
        {
            "type": "negative",
            "shape": "cylinder",
            "r": 7.5,
            "h": 4,
            "inclusion": "3dpr",
            "depth": "bearing_6702_depth"
        },
        {
            "type": "negative",
            "shape": "cylinder",
            "r": 7.5,
            "h": 4,
            "inclusion": "true",
            "depth": "bearing_6702_depth"
        }
    ]
}